generate_reference_and_reads.py
libs/__init__.py
libs/simulations_libs.py
libs/variant_generation_libs.py
damaged_reads_simulator-0.1.1.dist-info/METADATA
damaged_reads_simulator-0.1.1.dist-info/WHEEL
damaged_reads_simulator-0.1.1.dist-info/entry_points.txt
damaged_reads_simulator-0.1.1.dist-info/top_level.txt
damaged_reads_simulator-0.1.1.dist-info/RECORD
