Metadata-Version: 2.4
Name: damaged-reads-simulator
Version: 0.1.1
Summary: A simulator for damaged DNA reads with base quality recalibration
Home-page: https://github.com/nebiolabs/damaged_reads_simulator
Author: Ariel Erijman (NEB Labs) 
Author-email: Ariel Erijman <aerijman@neb.com>, Brad Langhorst <langhorst@neb.com>
Project-URL: Homepage, https://github.com/nebiolabs/damaged_reads_simulator
Project-URL: Repository, https://github.com/nebiolabs/damaged_reads_simulator
Project-URL: Issues, https://github.com/nebiolabs/damaged_reads_simulator/issues
Keywords: bioinformatics,dna,sequencing,simulation,base-quality
Classifier: Development Status :: 3 - Alpha
Classifier: Intended Audience :: Science/Research
Classifier: License :: OSI Approved :: MIT License
Classifier: Operating System :: OS Independent
Classifier: Programming Language :: Python :: 3
Classifier: Programming Language :: Python :: 3.8
Classifier: Programming Language :: Python :: 3.9
Classifier: Programming Language :: Python :: 3.10
Classifier: Programming Language :: Python :: 3.11
Classifier: Topic :: Scientific/Engineering :: Bio-Informatics
Requires-Python: >=3.8
Requires-Dist: numpy
Requires-Dist: scipy
Requires-Dist: pandas
Requires-Dist: matplotlib
Requires-Dist: seaborn
Requires-Dist: biopython
Requires-Dist: fast_string_replace
Provides-Extra: dev
Requires-Dist: pytest; extra == "dev"
Requires-Dist: pytest-cov; extra == "dev"
Requires-Dist: black; extra == "dev"
Requires-Dist: flake8; extra == "dev"
Requires-Dist: mypy; extra == "dev"
Dynamic: author
Dynamic: home-page
Dynamic: requires-python
